Workbook

Sheet Start Here
C2: Freelancer Income & Tax Tracker
C3: Log what comes in and what goes out, see income minus deductible expenses each month, and know how much to set aside for tax. Works in Microsoft Excel and Google Sheets.
C5: HOW TO USE IT
B6: 1 | C6: Open Setup. Enter the tax year, your business name, the % of income minus deductible expenses you want to set aside for tax, and an optional monthly income goal.
B7: 2 | C7: Still on Setup: list your clients and check the expense categories. Change the names or deductible % to fit your work.
B8: 3 | C8: Log every payment you receive on Income, and every business cost on Expenses. Dropdowns fill from Setup.
B9: 4 | C9: Use Invoices to track what you have billed. Overdue invoices turn red.
B10: 5 | C10: Check Monthly & Tax for income minus deductible expenses and set-aside per month and per quarter. A loss month shows a negative set-aside (money you no longer need to add). Record tax payments you make there.
B11: 6 | C11: Dashboard and Breakdown update on their own.
C13: CELL COLOURS
C14: Cream cells are for typing. Everything else calculates on its own.
C16: GOOD TO KNOW
C17: Google Sheets: upload the file to Google Drive, then open it with Google Sheets (or File > Import).
C18: Dollar signs are just formatting. To change currency, select the cells and use Format > Number.
C19: Room for 500 income rows, 500 expense rows and 200 invoices. Start a fresh copy each tax year.
C20: An expense with no category, or a category not listed on Setup, counts as 0% deductible until you pick one.
C21: This tracker helps you save for tax. It does not calculate the tax you owe and is not tax advice. Talk to a tax professional about your situation.
C22: Please do not type over the white formula cells. If something breaks, re-download the original from Etsy (Purchases > Download files).

Sheet Dashboard
B2: Dashboard
B3: =Setup!$C$7&" · "&Setup!$C$6
B6: INCOME | E6: DEDUCTIBLE EXPENSES | H6: INCOME MINUS DEDUCTIBLE | K6: ALL EXPENSES
B7: ='Monthly & Tax'!C19 | E7: ='Monthly & Tax'!E19 | H7: ='Monthly & Tax'!F19 | K7: ='Monthly & Tax'!D19
B9: SET ASIDE FOR TAX | E9: TAX PAID SO FAR | H9: UNPAID INVOICES | K9: OVERDUE INVOICES
B10: ='Monthly & Tax'!I19 | E10: =SUM('Monthly & Tax'!H24:H27) | H10: =Invoices!D5 | K10: =Invoices!G5

Sheet Setup
B2: Setup
B3: Fill this in once. Every other tab reads from here.
B6: Tax year | C6: 2026
B7: Business name | C7: My Freelance Business
B8: Tax set-aside % | C8: 0.25 | E8: The share of income minus deductible expenses you move to savings for tax. Ask a tax professional what fits you.
B9: Monthly income goal | C9: 0
B13: Your clients | E13: Expense categories | F13: Deductible %
E14: Advertising & marketing | F14: 1
E15: Software & subscriptions | F15: 1
E16: Office supplies | F16: 1
E17: Equipment & computers | F17: 1
E18: Phone & internet | F18: 1
E19: Professional services | F19: 1
E20: Contractors | F20: 1
E21: Travel | F21: 1
E22: Business meals | F22: 0.5
E23: Education & training | F23: 1
E24: Bank & payment fees | F24: 1
E25: Business insurance | F25: 1
... E31: Other | F31: 1
E35: Deductible % is the share of that cost you can claim. Rules differ by country;
E36: for example, US business meals are usually 50% deductible. Check with a tax pro.

Sheet Income
B2: Income
B3: Log money when it lands in your account. One row per payment.
B5: ="Total received in "&Setup!$C$6&":" | E5: =SUMIFS(F7:F506,B7:B506,">="&DATE(Setup!$C$6,1,1),B7:B506,"<"&DATE(Setup!$C$6+1,1,1))
B6: Date received | C6: Client | D6: What it was for | E6: Invoice # | F6: Amount | G6: Paid by | H6: Notes

Sheet Expenses
B2: Expenses
B3: Every business cost. Pick a category and the deductible part fills in.
B5: ="Deductible total in "&Setup!$C$6&":" | E5: =SUMIFS(H7:H506,B7:B506,">="&DATE(Setup!$C$6,1,1),B7:B506,"<"&DATE(Setup!$C$6+1,1,1))
B6: Date | C6: Paid to | D6: Category | E6: What it was | F6: Amount | G6: Deductible % | H6: Deductible amount | I6: Receipt saved?
G7: =IF(D7="","",IFERROR(N(INDEX(Setup!$F$14:$F$33,MATCH(D7,Setup!$E$14:$E$33,0))),0)) | H7: =IF(OR(F7="",G7=""),"",F7*G7)
G8: =IF(D8="","",IFERROR(N(INDEX(Setup!$F$14:$F$33,MATCH(D8,Setup!$E$14:$E$33,0))),0)) | H8: =IF(OR(F8="",G8=""),"",F8*G8)
G9: =IF(D9="","",IFERROR(N(INDEX(Setup!$F$14:$F$33,MATCH(D9,Setup!$E$14:$E$33,0))),0)) | H9: =IF(OR(F9="",G9=""),"",F9*G9)
G10: =IF(D10="","",IFERROR(N(INDEX(Setup!$F$14:$F$33,MATCH(D10,Setup!$E$14:$E$33,0))),0)) | H10: =IF(OR(F10="",G10=""),"",F10*G10)
G11: =IF(D11="","",IFERROR(N(INDEX(Setup!$F$14:$F$33,MATCH(D11,Setup!$E$14:$E$33,0))),0)) | H11: =IF(OR(F11="",G11=""),"",F11*G11)
G12: =IF(D12="","",IFERROR(N(INDEX(Setup!$F$14:$F$33,MATCH(D12,Setup!$E$14:$E$33,0))),0)) | H12: =IF(OR(F12="",G12=""),"",F12*G12)
G13: =IF(D13="","",IFERROR(N(INDEX(Setup!$F$14:$F$33,MATCH(D13,Setup!$E$14:$E$33,0))),0)) | H13: =IF(OR(F13="",G13=""),"",F13*G13)
G14: =IF(D14="","",IFERROR(N(INDEX(Setup!$F$14:$F$33,MATCH(D14,Setup!$E$14:$E$33,0))),0)) | H14: =IF(OR(F14="",G14=""),"",F14*G14)
G15: =IF(D15="","",IFERROR(N(INDEX(Setup!$F$14:$F$33,MATCH(D15,Setup!$E$14:$E$33,0))),0)) | H15: =IF(OR(F15="",G15=""),"",F15*G15)
G16: =IF(D16="","",IFERROR(N(INDEX(Setup!$F$14:$F$33,MATCH(D16,Setup!$E$14:$E$33,0))),0)) | H16: =IF(OR(F16="",G16=""),"",F16*G16)
G17: =IF(D17="","",IFERROR(N(INDEX(Setup!$F$14:$F$33,MATCH(D17,Setup!$E$14:$E$33,0))),0)) | H17: =IF(OR(F17="",G17=""),"",F17*G17)
G18: =IF(D18="","",IFERROR(N(INDEX(Setup!$F$14:$F$33,MATCH(D18,Setup!$E$14:$E$33,0))),0)) | H18: =IF(OR(F18="",G18=""),"",F18*G18)
... G506: =IF(D506="","",IFERROR(N(INDEX(Setup!$F$14:$F$33,MATCH(D506,Setup!$E$14:$E$33,0))),0)) | H506: =IF(OR(F506="",G506=""),"",F506*G506)

Sheet Invoices
B2: Invoices
B3: Track what you have billed and who still owes you.
B5: Still unpaid: | D5: =SUMIFS(F7:F206,G7:G206,"<>Yes") | F5: Overdue: | G5: =COUNTIF(I7:I206,"Overdue*")
B6: Invoice # | C6: Client | D6: Date sent | E6: Due date | F6: Amount | G6: Paid? | H6: Date paid | I6: Status | J6: Notes
I7: =IF(F7="","",IF(G7="Yes","Paid",IF(E7="","Unpaid",IF(TODAY()>E7,"Overdue "&(TODAY()-E7)&" days","Due in "&(E7-TODAY())&" days"))))
I8: =IF(F8="","",IF(G8="Yes","Paid",IF(E8="","Unpaid",IF(TODAY()>E8,"Overdue "&(TODAY()-E8)&" days","Due in "&(E8-TODAY())&" days"))))
I9: =IF(F9="","",IF(G9="Yes","Paid",IF(E9="","Unpaid",IF(TODAY()>E9,"Overdue "&(TODAY()-E9)&" days","Due in "&(E9-TODAY())&" days"))))
I10: =IF(F10="","",IF(G10="Yes","Paid",IF(E10="","Unpaid",IF(TODAY()>E10,"Overdue "&(TODAY()-E10)&" days","Due in "&(E10-TODAY())&" days"))))
I11: =IF(F11="","",IF(G11="Yes","Paid",IF(E11="","Unpaid",IF(TODAY()>E11,"Overdue "&(TODAY()-E11)&" days","Due in "&(E11-TODAY())&" days"))))
I12: =IF(F12="","",IF(G12="Yes","Paid",IF(E12="","Unpaid",IF(TODAY()>E12,"Overdue "&(TODAY()-E12)&" days","Due in "&(E12-TODAY())&" days"))))
I13: =IF(F13="","",IF(G13="Yes","Paid",IF(E13="","Unpaid",IF(TODAY()>E13,"Overdue "&(TODAY()-E13)&" days","Due in "&(E13-TODAY())&" days"))))
I14: =IF(F14="","",IF(G14="Yes","Paid",IF(E14="","Unpaid",IF(TODAY()>E14,"Overdue "&(TODAY()-E14)&" days","Due in "&(E14-TODAY())&" days"))))
I15: =IF(F15="","",IF(G15="Yes","Paid",IF(E15="","Unpaid",IF(TODAY()>E15,"Overdue "&(TODAY()-E15)&" days","Due in "&(E15-TODAY())&" days"))))
I16: =IF(F16="","",IF(G16="Yes","Paid",IF(E16="","Unpaid",IF(TODAY()>E16,"Overdue "&(TODAY()-E16)&" days","Due in "&(E16-TODAY())&" days"))))
I17: =IF(F17="","",IF(G17="Yes","Paid",IF(E17="","Unpaid",IF(TODAY()>E17,"Overdue "&(TODAY()-E17)&" days","Due in "&(E17-TODAY())&" days"))))
I18: =IF(F18="","",IF(G18="Yes","Paid",IF(E18="","Unpaid",IF(TODAY()>E18,"Overdue "&(TODAY()-E18)&" days","Due in "&(E18-TODAY())&" days"))))
... I206: =IF(F206="","",IF(G206="Yes","Paid",IF(E206="","Unpaid",IF(TODAY()>E206,"Overdue "&(TODAY()-E206)&" days","Due in "&(E206-TODAY())&" days"))))

Sheet Monthly & Tax
B2: Monthly summary & tax set-aside
B3: =Setup!$C$7&" · "&Setup!$C$6&" · setting aside "&TEXT(Setup!$C$8,"0%")&" of income minus deductible expenses"
B6: Month | C6: Income | D6: All expenses | E6: Deductible expenses | F6: Income minus deductible | G6: Year so far (income minus deductible) | H6: Set aside this month | I6: Set aside so far | J6: Income goal | K6: vs goal
B7: =DATE(Setup!$C$6,1,1) | C7: =SUMIFS(Income!$F$7:$F$506,Income!$B$7:$B$506,">="&DATE(Setup!$C$6,1,1),Income!$B$7:$B$506,"<"&DATE(Setup!$C$6,2,1)) | D7: =SUMIFS(Expenses!$F$7:$F$506,Expenses!$B$7:$B$506,">="&DATE(Setup!$C$6,1,1),Expenses!$B$7:$B$506,"<"&DATE(Setup!$C$6,2,1)) | E7: =SUMIFS(Expenses!$H$7:$H$506,Expenses!$B$7:$B$506,">="&DATE(Setup!$C$6,1,1),Expenses!$B$7:$B$506,"<"&DATE(Setup!$C$6,2,1)) | F7: =C7-E7 | G7: =SUM($F$7:F7) | H7: =I7 | I7: =MAX(0,G7)*Setup!$C$8 | J7: =Setup!$C$9 | K7: =IF(J7>0,C7/J7,"")
B8: =DATE(Setup!$C$6,2,1) | C8: =SUMIFS(Income!$F$7:$F$506,Income!$B$7:$B$506,">="&DATE(Setup!$C$6,2,1),Income!$B$7:$B$506,"<"&DATE(Setup!$C$6,3,1)) | D8: =SUMIFS(Expenses!$F$7:$F$506,Expenses!$B$7:$B$506,">="&DATE(Setup!$C$6,2,1),Expenses!$B$7:$B$506,"<"&DATE(Setup!$C$6,3,1)) | E8: =SUMIFS(Expenses!$H$7:$H$506,Expenses!$B$7:$B$506,">="&DATE(Setup!$C$6,2,1),Expenses!$B$7:$B$506,"<"&DATE(Setup!$C$6,3,1)) | F8: =C8-E8 | G8: =SUM($F$7:F8) | H8: =I8-I7 | I8: =MAX(0,G8)*Setup!$C$8 | J8: =Setup!$C$9 | K8: =IF(J8>0,C8/J8,"")
B9: =DATE(Setup!$C$6,3,1) | C9: =SUMIFS(Income!$F$7:$F$506,Income!$B$7:$B$506,">="&DATE(Setup!$C$6,3,1),Income!$B$7:$B$506,"<"&DATE(Setup!$C$6,4,1)) | D9: =SUMIFS(Expenses!$F$7:$F$506,Expenses!$B$7:$B$506,">="&DATE(Setup!$C$6,3,1),Expenses!$B$7:$B$506,"<"&DATE(Setup!$C$6,4,1)) | E9: =SUMIFS(Expenses!$H$7:$H$506,Expenses!$B$7:$B$506,">="&DATE(Setup!$C$6,3,1),Expenses!$B$7:$B$506,"<"&DATE(Setup!$C$6,4,1)) | F9: =C9-E9 | G9: =SUM($F$7:F9) | H9: =I9-I8 | I9: =MAX(0,G9)*Setup!$C$8 | J9: =Setup!$C$9 | K9: =IF(J9>0,C9/J9,"")
B10: =DATE(Setup!$C$6,4,1) | C10: =SUMIFS(Income!$F$7:$F$506,Income!$B$7:$B$506,">="&DATE(Setup!$C$6,4,1),Income!$B$7:$B$506,"<"&DATE(Setup!$C$6,5,1)) | D10: =SUMIFS(Expenses!$F$7:$F$506,Expenses!$B$7:$B$506,">="&DATE(Setup!$C$6,4,1),Expenses!$B$7:$B$506,"<"&DATE(Setup!$C$6,5,1)) | E10: =SUMIFS(Expenses!$H$7:$H$506,Expenses!$B$7:$B$506,">="&DATE(Setup!$C$6,4,1),Expenses!$B$7:$B$506,"<"&DATE(Setup!$C$6,5,1)) | F10: =C10-E10 | G10: =SUM($F$7:F10) | H10: =I10-I9 | I10: =MAX(0,G10)*Setup!$C$8 | J10: =Setup!$C$9 | K10: =IF(J10>0,C10/J10,"")
B11: =DATE(Setup!$C$6,5,1) | C11: =SUMIFS(Income!$F$7:$F$506,Income!$B$7:$B$506,">="&DATE(Setup!$C$6,5,1),Income!$B$7:$B$506,"<"&DATE(Setup!$C$6,6,1)) | D11: =SUMIFS(Expenses!$F$7:$F$506,Expenses!$B$7:$B$506,">="&DATE(Setup!$C$6,5,1),Expenses!$B$7:$B$506,"<"&DATE(Setup!$C$6,6,1)) | E11: =SUMIFS(Expenses!$H$7:$H$506,Expenses!$B$7:$B$506,">="&DATE(Setup!$C$6,5,1),Expenses!$B$7:$B$506,"<"&DATE(Setup!$C$6,6,1)) | F11: =C11-E11 | G11: =SUM($F$7:F11) | H11: =I11-I10 | I11: =MAX(0,G11)*Setup!$C$8 | J11: =Setup!$C$9 | K11: =IF(J11>0,C11/J11,"")
B12: =DATE(Setup!$C$6,6,1) | C12: =SUMIFS(Income!$F$7:$F$506,Income!$B$7:$B$506,">="&DATE(Setup!$C$6,6,1),Income!$B$7:$B$506,"<"&DATE(Setup!$C$6,7,1)) | D12: =SUMIFS(Expenses!$F$7:$F$506,Expenses!$B$7:$B$506,">="&DATE(Setup!$C$6,6,1),Expenses!$B$7:$B$506,"<"&DATE(Setup!$C$6,7,1)) | E12: =SUMIFS(Expenses!$H$7:$H$506,Expenses!$B$7:$B$506,">="&DATE(Setup!$C$6,6,1),Expenses!$B$7:$B$506,"<"&DATE(Setup!$C$6,7,1)) | F12: =C12-E12 | G12: =SUM($F$7:F12) | H12: =I12-I11 | I12: =MAX(0,G12)*Setup!$C$8 | J12: =Setup!$C$9 | K12: =IF(J12>0,C12/J12,"")
B13: =DATE(Setup!$C$6,7,1) | C13: =SUMIFS(Income!$F$7:$F$506,Income!$B$7:$B$506,">="&DATE(Setup!$C$6,7,1),Income!$B$7:$B$506,"<"&DATE(Setup!$C$6,8,1)) | D13: =SUMIFS(Expenses!$F$7:$F$506,Expenses!$B$7:$B$506,">="&DATE(Setup!$C$6,7,1),Expenses!$B$7:$B$506,"<"&DATE(Setup!$C$6,8,1)) | E13: =SUMIFS(Expenses!$H$7:$H$506,Expenses!$B$7:$B$506,">="&DATE(Setup!$C$6,7,1),Expenses!$B$7:$B$506,"<"&DATE(Setup!$C$6,8,1)) | F13: =C13-E13 | G13: =SUM($F$7:F13) | H13: =I13-I12 | I13: =MAX(0,G13)*Setup!$C$8 | J13: =Setup!$C$9 | K13: =IF(J13>0,C13/J13,"")
B14: =DATE(Setup!$C$6,8,1) | C14: =SUMIFS(Income!$F$7:$F$506,Income!$B$7:$B$506,">="&DATE(Setup!$C$6,8,1),Income!$B$7:$B$506,"<"&DATE(Setup!$C$6,9,1)) | D14: =SUMIFS(Expenses!$F$7:$F$506,Expenses!$B$7:$B$506,">="&DATE(Setup!$C$6,8,1),Expenses!$B$7:$B$506,"<"&DATE(Setup!$C$6,9,1)) | E14: =SUMIFS(Expenses!$H$7:$H$506,Expenses!$B$7:$B$506,">="&DATE(Setup!$C$6,8,1),Expenses!$B$7:$B$506,"<"&DATE(Setup!$C$6,9,1)) | F14: =C14-E14 | G14: =SUM($F$7:F14) | H14: =I14-I13 | I14: =MAX(0,G14)*Setup!$C$8 | J14: =Setup!$C$9 | K14: =IF(J14>0,C14/J14,"")
B15: =DATE(Setup!$C$6,9,1) | C15: =SUMIFS(Income!$F$7:$F$506,Income!$B$7:$B$506,">="&DATE(Setup!$C$6,9,1),Income!$B$7:$B$506,"<"&DATE(Setup!$C$6,10,1)) | D15: =SUMIFS(Expenses!$F$7:$F$506,Expenses!$B$7:$B$506,">="&DATE(Setup!$C$6,9,1),Expenses!$B$7:$B$506,"<"&DATE(Setup!$C$6,10,1)) | E15: =SUMIFS(Expenses!$H$7:$H$506,Expenses!$B$7:$B$506,">="&DATE(Setup!$C$6,9,1),Expenses!$B$7:$B$506,"<"&DATE(Setup!$C$6,10,1)) | F15: =C15-E15 | G15: =SUM($F$7:F15) | H15: =I15-I14 | I15: =MAX(0,G15)*Setup!$C$8 | J15: =Setup!$C$9 | K15: =IF(J15>0,C15/J15,"")
B16: =DATE(Setup!$C$6,10,1) | C16: =SUMIFS(Income!$F$7:$F$506,Income!$B$7:$B$506,">="&DATE(Setup!$C$6,10,1),Income!$B$7:$B$506,"<"&DATE(Setup!$C$6,11,1)) | D16: =SUMIFS(Expenses!$F$7:$F$506,Expenses!$B$7:$B$506,">="&DATE(Setup!$C$6,10,1),Expenses!$B$7:$B$506,"<"&DATE(Setup!$C$6,11,1)) | E16: =SUMIFS(Expenses!$H$7:$H$506,Expenses!$B$7:$B$506,">="&DATE(Setup!$C$6,10,1),Expenses!$B$7:$B$506,"<"&DATE(Setup!$C$6,11,1)) | F16: =C16-E16 | G16: =SUM($F$7:F16) | H16: =I16-I15 | I16: =MAX(0,G16)*Setup!$C$8 | J16: =Setup!$C$9 | K16: =IF(J16>0,C16/J16,"")
B17: =DATE(Setup!$C$6,11,1) | C17: =SUMIFS(Income!$F$7:$F$506,Income!$B$7:$B$506,">="&DATE(Setup!$C$6,11,1),Income!$B$7:$B$506,"<"&DATE(Setup!$C$6,12,1)) | D17: =SUMIFS(Expenses!$F$7:$F$506,Expenses!$B$7:$B$506,">="&DATE(Setup!$C$6,11,1),Expenses!$B$7:$B$506,"<"&DATE(Setup!$C$6,12,1)) | E17: =SUMIFS(Expenses!$H$7:$H$506,Expenses!$B$7:$B$506,">="&DATE(Setup!$C$6,11,1),Expenses!$B$7:$B$506,"<"&DATE(Setup!$C$6,12,1)) | F17: =C17-E17 | G17: =SUM($F$7:F17) | H17: =I17-I16 | I17: =MAX(0,G17)*Setup!$C$8 | J17: =Setup!$C$9 | K17: =IF(J17>0,C17/J17,"")
B18: =DATE(Setup!$C$6,12,1) | C18: =SUMIFS(Income!$F$7:$F$506,Income!$B$7:$B$506,">="&DATE(Setup!$C$6,12,1),Income!$B$7:$B$506,"<"&DATE(Setup!$C$6,13,1)) | D18: =SUMIFS(Expenses!$F$7:$F$506,Expenses!$B$7:$B$506,">="&DATE(Setup!$C$6,12,1),Expenses!$B$7:$B$506,"<"&DATE(Setup!$C$6,13,1)) | E18: =SUMIFS(Expenses!$H$7:$H$506,Expenses!$B$7:$B$506,">="&DATE(Setup!$C$6,12,1),Expenses!$B$7:$B$506,"<"&DATE(Setup!$C$6,13,1)) | F18: =C18-E18 | G18: =SUM($F$7:F18) | H18: =I18-I17 | I18: =MAX(0,G18)*Setup!$C$8 | J18: =Setup!$C$9 | K18: =IF(J18>0,C18/J18,"")
B19: Year total | C19: =SUM(C7:C18) | D19: =SUM(D7:D18) | E19: =SUM(E7:E18) | F19: =SUM(F7:F18) | G19: =G18 | H19: =SUM(H7:H18) | I19: =I18
B22: QUARTERLY TAX SET-ASIDE
B23: Quarter | C23: Income | D23: Deductible expenses | E23: Income minus deductible | F23: Set aside for this quarter | G23: Due date | H23: Amount paid | I23: Date paid | J23: Set aside so far minus paid so far
B24: Q1 (Jan-Mar) | C24: =SUM(C7:C9) | D24: =SUM(E7:E9) | E24: =C24-D24 | F24: =I9 | G24: =DATE(Setup!$C$6,4,15) | J24: =I9-SUM($H$24:H24)
B25: Q2 (Apr-May) | C25: =SUM(C10:C11) | D25: =SUM(E10:E11) | E25: =C25-D25 | F25: =I11-I9 | G25: =DATE(Setup!$C$6,6,15) | J25: =I11-SUM($H$24:H25)
B26: Q3 (Jun-Aug) | C26: =SUM(C12:C14) | D26: =SUM(E12:E14) | E26: =C26-D26 | F26: =I14-I11 | G26: =DATE(Setup!$C$6,9,15) | J26: =I14-SUM($H$24:H26)
B27: Q4 (Sep-Dec) | C27: =SUM(C15:C18) | D27: =SUM(E15:E18) | E27: =C27-D27 | F27: =I18-I14 | G27: =DATE(Setup!$C$6+1,1,15) | J27: =I18-SUM($H$24:H27)
B28: Year total | C28: =SUM(C24:C27) | D28: =SUM(D24:D27) | E28: =SUM(E24:E27) | F28: =SUM(F24:F27) | H28: =SUM(H24:H27) | J28: =J27
B30: How set-aside works: it is always your set-aside % of the year so far (income minus deductible expenses), never below zero. A loss month or quarter lowers that figure, so its set-aside shows as a negative amount: money you already put aside that you no longer need to add. The year total always equals your % of the full year's income minus deductible expenses.
B33: Income minus deductible expenses is not your final taxable profit: things like self-employment tax, allowances and other income are not included. Quarters and due dates follow the US federal estimated-tax schedule (weekends and holidays can move them); outside the US, type your own. This is a savings guide, not a tax calculation.

Sheet Breakdown
B2: Where it comes from, where it goes
B3: ="Totals for "&Setup!$C$6
B6: Expense category | C6: Spent | D6: Deductible | E6: % of spend | G6: Client | H6: Income | I6: Payments | J6: % of income
B7: =IF(Setup!E14="","",Setup!E14) | C7: =IF($B7="","",SUMIFS(Expenses!$F$7:$F$506,Expenses!$D$7:$D$506,$B7,Expenses!$B$7:$B$506,">="&DATE(Setup!$C$6,1,1),Expenses!$B$7:$B$506,"<"&DATE(Setup!$C$6+1,1,1))) | D7: =IF($B7="","",SUMIFS(Expenses!$H$7:$H$506,Expenses!$D$7:$D$506,$B7,Expenses!$B$7:$B$506,">="&DATE(Setup!$C$6,1,1),Expenses!$B$7:$B$506,"<"&DATE(Setup!$C$6+1,1,1))) | E7: =IF(OR($B7="",SUM($C$7:$C$26)=0),"",C7/SUM($C$7:$C$26)) | G7: =IF(Setup!B14="","",Setup!B14) | H7: =IF($G7="","",SUMIFS(Income!$F$7:$F$506,Income!$C$7:$C$506,$G7,Income!$B$7:$B$506,">="&DATE(Setup!$C$6,1,1),Income!$B$7:$B$506,"<"&DATE(Setup!$C$6+1,1,1))) | I7: =IF($G7="","",COUNTIFS(Income!$C$7:$C$506,$G7,Income!$B$7:$B$506,">="&DATE(Setup!$C$6,1,1),Income!$B$7:$B$506,"<"&DATE(Setup!$C$6+1,1,1))) | J7: =IF(OR($G7="",SUM($H$7:$H$36)=0),"",H7/SUM($H$7:$H$36))
B8: =IF(Setup!E15="","",Setup!E15) | C8: =IF($B8="","",SUMIFS(Expenses!$F$7:$F$506,Expenses!$D$7:$D$506,$B8,Expenses!$B$7:$B$506,">="&DATE(Setup!$C$6,1,1),Expenses!$B$7:$B$506,"<"&DATE(Setup!$C$6+1,1,1))) | D8: =IF($B8="","",SUMIFS(Expenses!$H$7:$H$506,Expenses!$D$7:$D$506,$B8,Expenses!$B$7:$B$506,">="&DATE(Setup!$C$6,1,1),Expenses!$B$7:$B$506,"<"&DATE(Setup!$C$6+1,1,1))) | E8: =IF(OR($B8="",SUM($C$7:$C$26)=0),"",C8/SUM($C$7:$C$26)) | G8: =IF(Setup!B15="","",Setup!B15) | H8: =IF($G8="","",SUMIFS(Income!$F$7:$F$506,Income!$C$7:$C$506,$G8,Income!$B$7:$B$506,">="&DATE(Setup!$C$6,1,1),Income!$B$7:$B$506,"<"&DATE(Setup!$C$6+1,1,1))) | I8: =IF($G8="","",COUNTIFS(Income!$C$7:$C$506,$G8,Income!$B$7:$B$506,">="&DATE(Setup!$C$6,1,1),Income!$B$7:$B$506,"<"&DATE(Setup!$C$6+1,1,1))) | J8: =IF(OR($G8="",SUM($H$7:$H$36)=0),"",H8/SUM($H$7:$H$36))
B9: =IF(Setup!E16="","",Setup!E16) | C9: =IF($B9="","",SUMIFS(Expenses!$F$7:$F$506,Expenses!$D$7:$D$506,$B9,Expenses!$B$7:$B$506,">="&DATE(Setup!$C$6,1,1),Expenses!$B$7:$B$506,"<"&DATE(Setup!$C$6+1,1,1))) | D9: =IF($B9="","",SUMIFS(Expenses!$H$7:$H$506,Expenses!$D$7:$D$506,$B9,Expenses!$B$7:$B$506,">="&DATE(Setup!$C$6,1,1),Expenses!$B$7:$B$506,"<"&DATE(Setup!$C$6+1,1,1))) | E9: =IF(OR($B9="",SUM($C$7:$C$26)=0),"",C9/SUM($C$7:$C$26)) | G9: =IF(Setup!B16="","",Setup!B16) | H9: =IF($G9="","",SUMIFS(Income!$F$7:$F$506,Income!$C$7:$C$506,$G9,Income!$B$7:$B$506,">="&DATE(Setup!$C$6,1,1),Income!$B$7:$B$506,"<"&DATE(Setup!$C$6+1,1,1))) | I9: =IF($G9="","",COUNTIFS(Income!$C$7:$C$506,$G9,Income!$B$7:$B$506,">="&DATE(Setup!$C$6,1,1),Income!$B$7:$B$506,"<"&DATE(Setup!$C$6+1,1,1))) | J9: =IF(OR($G9="",SUM($H$7:$H$36)=0),"",H9/SUM($H$7:$H$36))
B10: =IF(Setup!E17="","",Setup!E17) | C10: =IF($B10="","",SUMIFS(Expenses!$F$7:$F$506,Expenses!$D$7:$D$506,$B10,Expenses!$B$7:$B$506,">="&DATE(Setup!$C$6,1,1),Expenses!$B$7:$B$506,"<"&DATE(Setup!$C$6+1,1,1))) | D10: =IF($B10="","",SUMIFS(Expenses!$H$7:$H$506,Expenses!$D$7:$D$506,$B10,Expenses!$B$7:$B$506,">="&DATE(Setup!$C$6,1,1),Expenses!$B$7:$B$506,"<"&DATE(Setup!$C$6+1,1,1))) | E10: =IF(OR($B10="",SUM($C$7:$C$26)=0),"",C10/SUM($C$7:$C$26)) | G10: =IF(Setup!B17="","",Setup!B17) | H10: =IF($G10="","",SUMIFS(Income!$F$7:$F$506,Income!$C$7:$C$506,$G10,Income!$B$7:$B$506,">="&DATE(Setup!$C$6,1,1),Income!$B$7:$B$506,"<"&DATE(Setup!$C$6+1,1,1))) | I10: =IF($G10="","",COUNTIFS(Income!$C$7:$C$506,$G10,Income!$B$7:$B$506,">="&DATE(Setup!$C$6,1,1),Income!$B$7:$B$506,"<"&DATE(Setup!$C$6+1,1,1))) | J10: =IF(OR($G10="",SUM($H$7:$H$36)=0),"",H10/SUM($H$7:$H$36))
B11: =IF(Setup!E18="","",Setup!E18) | C11: =IF($B11="","",SUMIFS(Expenses!$F$7:$F$506,Expenses!$D$7:$D$506,$B11,Expenses!$B$7:$B$506,">="&DATE(Setup!$C$6,1,1),Expenses!$B$7:$B$506,"<"&DATE(Setup!$C$6+1,1,1))) | D11: =IF($B11="","",SUMIFS(Expenses!$H$7:$H$506,Expenses!$D$7:$D$506,$B11,Expenses!$B$7:$B$506,">="&DATE(Setup!$C$6,1,1),Expenses!$B$7:$B$506,"<"&DATE(Setup!$C$6+1,1,1))) | E11: =IF(OR($B11="",SUM($C$7:$C$26)=0),"",C11/SUM($C$7:$C$26)) | G11: =IF(Setup!B18="","",Setup!B18) | H11: =IF($G11="","",SUMIFS(Income!$F$7:$F$506,Income!$C$7:$C$506,$G11,Income!$B$7:$B$506,">="&DATE(Setup!$C$6,1,1),Income!$B$7:$B$506,"<"&DATE(Setup!$C$6+1,1,1))) | I11: =IF($G11="","",COUNTIFS(Income!$C$7:$C$506,$G11,Income!$B$7:$B$506,">="&DATE(Setup!$C$6,1,1),Income!$B$7:$B$506,"<"&DATE(Setup!$C$6+1,1,1))) | J11: =IF(OR($G11="",SUM($H$7:$H$36)=0),"",H11/SUM($H$7:$H$36))
B12: =IF(Setup!E19="","",Setup!E19) | C12: =IF($B12="","",SUMIFS(Expenses!$F$7:$F$506,Expenses!$D$7:$D$506,$B12,Expenses!$B$7:$B$506,">="&DATE(Setup!$C$6,1,1),Expenses!$B$7:$B$506,"<"&DATE(Setup!$C$6+1,1,1))) | D12: =IF($B12="","",SUMIFS(Expenses!$H$7:$H$506,Expenses!$D$7:$D$506,$B12,Expenses!$B$7:$B$506,">="&DATE(Setup!$C$6,1,1),Expenses!$B$7:$B$506,"<"&DATE(Setup!$C$6+1,1,1))) | E12: =IF(OR($B12="",SUM($C$7:$C$26)=0),"",C12/SUM($C$7:$C$26)) | G12: =IF(Setup!B19="","",Setup!B19) | H12: =IF($G12="","",SUMIFS(Income!$F$7:$F$506,Income!$C$7:$C$506,$G12,Income!$B$7:$B$506,">="&DATE(Setup!$C$6,1,1),Income!$B$7:$B$506,"<"&DATE(Setup!$C$6+1,1,1))) | I12: =IF($G12="","",COUNTIFS(Income!$C$7:$C$506,$G12,Income!$B$7:$B$506,">="&DATE(Setup!$C$6,1,1),Income!$B$7:$B$506,"<"&DATE(Setup!$C$6+1,1,1))) | J12: =IF(OR($G12="",SUM($H$7:$H$36)=0),"",H12/SUM($H$7:$H$36))
B13: =IF(Setup!E20="","",Setup!E20) | C13: =IF($B13="","",SUMIFS(Expenses!$F$7:$F$506,Expenses!$D$7:$D$506,$B13,Expenses!$B$7:$B$506,">="&DATE(Setup!$C$6,1,1),Expenses!$B$7:$B$506,"<"&DATE(Setup!$C$6+1,1,1))) | D13: =IF($B13="","",SUMIFS(Expenses!$H$7:$H$506,Expenses!$D$7:$D$506,$B13,Expenses!$B$7:$B$506,">="&DATE(Setup!$C$6,1,1),Expenses!$B$7:$B$506,"<"&DATE(Setup!$C$6+1,1,1))) | E13: =IF(OR($B13="",SUM($C$7:$C$26)=0),"",C13/SUM($C$7:$C$26)) | G13: =IF(Setup!B20="","",Setup!B20) | H13: =IF($G13="","",SUMIFS(Income!$F$7:$F$506,Income!$C$7:$C$506,$G13,Income!$B$7:$B$506,">="&DATE(Setup!$C$6,1,1),Income!$B$7:$B$506,"<"&DATE(Setup!$C$6+1,1,1))) | I13: =IF($G13="","",COUNTIFS(Income!$C$7:$C$506,$G13,Income!$B$7:$B$506,">="&DATE(Setup!$C$6,1,1),Income!$B$7:$B$506,"<"&DATE(Setup!$C$6+1,1,1))) | J13: =IF(OR($G13="",SUM($H$7:$H$36)=0),"",H13/SUM($H$7:$H$36))
B14: =IF(Setup!E21="","",Setup!E21) | C14: =IF($B14="","",SUMIFS(Expenses!$F$7:$F$506,Expenses!$D$7:$D$506,$B14,Expenses!$B$7:$B$506,">="&DATE(Setup!$C$6,1,1),Expenses!$B$7:$B$506,"<"&DATE(Setup!$C$6+1,1,1))) | D14: =IF($B14="","",SUMIFS(Expenses!$H$7:$H$506,Expenses!$D$7:$D$506,$B14,Expenses!$B$7:$B$506,">="&DATE(Setup!$C$6,1,1),Expenses!$B$7:$B$506,"<"&DATE(Setup!$C$6+1,1,1))) | E14: =IF(OR($B14="",SUM($C$7:$C$26)=0),"",C14/SUM($C$7:$C$26)) | G14: =IF(Setup!B21="","",Setup!B21) | H14: =IF($G14="","",SUMIFS(Income!$F$7:$F$506,Income!$C$7:$C$506,$G14,Income!$B$7:$B$506,">="&DATE(Setup!$C$6,1,1),Income!$B$7:$B$506,"<"&DATE(Setup!$C$6+1,1,1))) | I14: =IF($G14="","",COUNTIFS(Income!$C$7:$C$506,$G14,Income!$B$7:$B$506,">="&DATE(Setup!$C$6,1,1),Income!$B$7:$B$506,"<"&DATE(Setup!$C$6+1,1,1))) | J14: =IF(OR($G14="",SUM($H$7:$H$36)=0),"",H14/SUM($H$7:$H$36))
B15: =IF(Setup!E22="","",Setup!E22) | C15: =IF($B15="","",SUMIFS(Expenses!$F$7:$F$506,Expenses!$D$7:$D$506,$B15,Expenses!$B$7:$B$506,">="&DATE(Setup!$C$6,1,1),Expenses!$B$7:$B$506,"<"&DATE(Setup!$C$6+1,1,1))) | D15: =IF($B15="","",SUMIFS(Expenses!$H$7:$H$506,Expenses!$D$7:$D$506,$B15,Expenses!$B$7:$B$506,">="&DATE(Setup!$C$6,1,1),Expenses!$B$7:$B$506,"<"&DATE(Setup!$C$6+1,1,1))) | E15: =IF(OR($B15="",SUM($C$7:$C$26)=0),"",C15/SUM($C$7:$C$26)) | G15: =IF(Setup!B22="","",Setup!B22) | H15: =IF($G15="","",SUMIFS(Income!$F$7:$F$506,Income!$C$7:$C$506,$G15,Income!$B$7:$B$506,">="&DATE(Setup!$C$6,1,1),Income!$B$7:$B$506,"<"&DATE(Setup!$C$6+1,1,1))) | I15: =IF($G15="","",COUNTIFS(Income!$C$7:$C$506,$G15,Income!$B$7:$B$506,">="&DATE(Setup!$C$6,1,1),Income!$B$7:$B$506,"<"&DATE(Setup!$C$6+1,1,1))) | J15: =IF(OR($G15="",SUM($H$7:$H$36)=0),"",H15/SUM($H$7:$H$36))
B16: =IF(Setup!E23="","",Setup!E23) | C16: =IF($B16="","",SUMIFS(Expenses!$F$7:$F$506,Expenses!$D$7:$D$506,$B16,Expenses!$B$7:$B$506,">="&DATE(Setup!$C$6,1,1),Expenses!$B$7:$B$506,"<"&DATE(Setup!$C$6+1,1,1))) | D16: =IF($B16="","",SUMIFS(Expenses!$H$7:$H$506,Expenses!$D$7:$D$506,$B16,Expenses!$B$7:$B$506,">="&DATE(Setup!$C$6,1,1),Expenses!$B$7:$B$506,"<"&DATE(Setup!$C$6+1,1,1))) | E16: =IF(OR($B16="",SUM($C$7:$C$26)=0),"",C16/SUM($C$7:$C$26)) | G16: =IF(Setup!B23="","",Setup!B23) | H16: =IF($G16="","",SUMIFS(Income!$F$7:$F$506,Income!$C$7:$C$506,$G16,Income!$B$7:$B$506,">="&DATE(Setup!$C$6,1,1),Income!$B$7:$B$506,"<"&DATE(Setup!$C$6+1,1,1))) | I16: =IF($G16="","",COUNTIFS(Income!$C$7:$C$506,$G16,Income!$B$7:$B$506,">="&DATE(Setup!$C$6,1,1),Income!$B$7:$B$506,"<"&DATE(Setup!$C$6+1,1,1))) | J16: =IF(OR($G16="",SUM($H$7:$H$36)=0),"",H16/SUM($H$7:$H$36))
B17: =IF(Setup!E24="","",Setup!E24) | C17: =IF($B17="","",SUMIFS(Expenses!$F$7:$F$506,Expenses!$D$7:$D$506,$B17,Expenses!$B$7:$B$506,">="&DATE(Setup!$C$6,1,1),Expenses!$B$7:$B$506,"<"&DATE(Setup!$C$6+1,1,1))) | D17: =IF($B17="","",SUMIFS(Expenses!$H$7:$H$506,Expenses!$D$7:$D$506,$B17,Expenses!$B$7:$B$506,">="&DATE(Setup!$C$6,1,1),Expenses!$B$7:$B$506,"<"&DATE(Setup!$C$6+1,1,1))) | E17: =IF(OR($B17="",SUM($C$7:$C$26)=0),"",C17/SUM($C$7:$C$26)) | G17: =IF(Setup!B24="","",Setup!B24) | H17: =IF($G17="","",SUMIFS(Income!$F$7:$F$506,Income!$C$7:$C$506,$G17,Income!$B$7:$B$506,">="&DATE(Setup!$C$6,1,1),Income!$B$7:$B$506,"<"&DATE(Setup!$C$6+1,1,1))) | I17: =IF($G17="","",COUNTIFS(Income!$C$7:$C$506,$G17,Income!$B$7:$B$506,">="&DATE(Setup!$C$6,1,1),Income!$B$7:$B$506,"<"&DATE(Setup!$C$6+1,1,1))) | J17: =IF(OR($G17="",SUM($H$7:$H$36)=0),"",H17/SUM($H$7:$H$36))
B18: =IF(Setup!E25="","",Setup!E25) | C18: =IF($B18="","",SUMIFS(Expenses!$F$7:$F$506,Expenses!$D$7:$D$506,$B18,Expenses!$B$7:$B$506,">="&DATE(Setup!$C$6,1,1),Expenses!$B$7:$B$506,"<"&DATE(Setup!$C$6+1,1,1))) | D18: =IF($B18="","",SUMIFS(Expenses!$H$7:$H$506,Expenses!$D$7:$D$506,$B18,Expenses!$B$7:$B$506,">="&DATE(Setup!$C$6,1,1),Expenses!$B$7:$B$506,"<"&DATE(Setup!$C$6+1,1,1))) | E18: =IF(OR($B18="",SUM($C$7:$C$26)=0),"",C18/SUM($C$7:$C$26)) | G18: =IF(Setup!B25="","",Setup!B25) | H18: =IF($G18="","",SUMIFS(Income!$F$7:$F$506,Income!$C$7:$C$506,$G18,Income!$B$7:$B$506,">="&DATE(Setup!$C$6,1,1),Income!$B$7:$B$506,"<"&DATE(Setup!$C$6+1,1,1))) | I18: =IF($G18="","",COUNTIFS(Income!$C$7:$C$506,$G18,Income!$B$7:$B$506,">="&DATE(Setup!$C$6,1,1),Income!$B$7:$B$506,"<"&DATE(Setup!$C$6+1,1,1))) | J18: =IF(OR($G18="",SUM($H$7:$H$36)=0),"",H18/SUM($H$7:$H$36))
... B26: =IF(Setup!E33="","",Setup!E33) | C26: =IF($B26="","",SUMIFS(Expenses!$F$7:$F$506,Expenses!$D$7:$D$506,$B26,Expenses!$B$7:$B$506,">="&DATE(Setup!$C$6,1,1),Expenses!$B$7:$B$506,"<"&DATE(Setup!$C$6+1,1,1))) | D26: =IF($B26="","",SUMIFS(Expenses!$H$7:$H$506,Expenses!$D$7:$D$506,$B26,Expenses!$B$7:$B$506,">="&DATE(Setup!$C$6,1,1),Expenses!$B$7:$B$506,"<"&DATE(Setup!$C$6+1,1,1))) | E26: =IF(OR($B26="",SUM($C$7:$C$26)=0),"",C26/SUM($C$7:$C$26)) | G26: =IF(Setup!B33="","",Setup!B33) | H26: =IF($G26="","",SUMIFS(Income!$F$7:$F$506,Income!$C$7:$C$506,$G26,Income!$B$7:$B$506,">="&DATE(Setup!$C$6,1,1),Income!$B$7:$B$506,"<"&DATE(Setup!$C$6+1,1,1))) | I26: =IF($G26="","",COUNTIFS(Income!$C$7:$C$506,$G26,Income!$B$7:$B$506,">="&DATE(Setup!$C$6,1,1),Income!$B$7:$B$506,"<"&DATE(Setup!$C$6+1,1,1))) | J26: =IF(OR($G26="",SUM($H$7:$H$36)=0),"",H26/SUM($H$7:$H$36))
G27: =IF(Setup!B34="","",Setup!B34) | H27: =IF($G27="","",SUMIFS(Income!$F$7:$F$506,Income!$C$7:$C$506,$G27,Income!$B$7:$B$506,">="&DATE(Setup!$C$6,1,1),Income!$B$7:$B$506,"<"&DATE(Setup!$C$6+1,1,1))) | I27: =IF($G27="","",COUNTIFS(Income!$C$7:$C$506,$G27,Income!$B$7:$B$506,">="&DATE(Setup!$C$6,1,1),Income!$B$7:$B$506,"<"&DATE(Setup!$C$6+1,1,1))) | J27: =IF(OR($G27="",SUM($H$7:$H$36)=0),"",H27/SUM($H$7:$H$36))
G28: =IF(Setup!B35="","",Setup!B35) | H28: =IF($G28="","",SUMIFS(Income!$F$7:$F$506,Income!$C$7:$C$506,$G28,Income!$B$7:$B$506,">="&DATE(Setup!$C$6,1,1),Income!$B$7:$B$506,"<"&DATE(Setup!$C$6+1,1,1))) | I28: =IF($G28="","",COUNTIFS(Income!$C$7:$C$506,$G28,Income!$B$7:$B$506,">="&DATE(Setup!$C$6,1,1),Income!$B$7:$B$506,"<"&DATE(Setup!$C$6+1,1,1))) | J28: =IF(OR($G28="",SUM($H$7:$H$36)=0),"",H28/SUM($H$7:$H$36))
G29: =IF(Setup!B36="","",Setup!B36) | H29: =IF($G29="","",SUMIFS(Income!$F$7:$F$506,Income!$C$7:$C$506,$G29,Income!$B$7:$B$506,">="&DATE(Setup!$C$6,1,1),Income!$B$7:$B$506,"<"&DATE(Setup!$C$6+1,1,1))) | I29: =IF($G29="","",COUNTIFS(Income!$C$7:$C$506,$G29,Income!$B$7:$B$506,">="&DATE(Setup!$C$6,1,1),Income!$B$7:$B$506,"<"&DATE(Setup!$C$6+1,1,1))) | J29: =IF(OR($G29="",SUM($H$7:$H$36)=0),"",H29/SUM($H$7:$H$36))
G30: =IF(Setup!B37="","",Setup!B37) | H30: =IF($G30="","",SUMIFS(Income!$F$7:$F$506,Income!$C$7:$C$506,$G30,Income!$B$7:$B$506,">="&DATE(Setup!$C$6,1,1),Income!$B$7:$B$506,"<"&DATE(Setup!$C$6+1,1,1))) | I30: =IF($G30="","",COUNTIFS(Income!$C$7:$C$506,$G30,Income!$B$7:$B$506,">="&DATE(Setup!$C$6,1,1),Income!$B$7:$B$506,"<"&DATE(Setup!$C$6+1,1,1))) | J30: =IF(OR($G30="",SUM($H$7:$H$36)=0),"",H30/SUM($H$7:$H$36))
G31: =IF(Setup!B38="","",Setup!B38) | H31: =IF($G31="","",SUMIFS(Income!$F$7:$F$506,Income!$C$7:$C$506,$G31,Income!$B$7:$B$506,">="&DATE(Setup!$C$6,1,1),Income!$B$7:$B$506,"<"&DATE(Setup!$C$6+1,1,1))) | I31: =IF($G31="","",COUNTIFS(Income!$C$7:$C$506,$G31,Income!$B$7:$B$506,">="&DATE(Setup!$C$6,1,1),Income!$B$7:$B$506,"<"&DATE(Setup!$C$6+1,1,1))) | J31: =IF(OR($G31="",SUM($H$7:$H$36)=0),"",H31/SUM($H$7:$H$36))
G32: =IF(Setup!B39="","",Setup!B39) | H32: =IF($G32="","",SUMIFS(Income!$F$7:$F$506,Income!$C$7:$C$506,$G32,Income!$B$7:$B$506,">="&DATE(Setup!$C$6,1,1),Income!$B$7:$B$506,"<"&DATE(Setup!$C$6+1,1,1))) | I32: =IF($G32="","",COUNTIFS(Income!$C$7:$C$506,$G32,Income!$B$7:$B$506,">="&DATE(Setup!$C$6,1,1),Income!$B$7:$B$506,"<"&DATE(Setup!$C$6+1,1,1))) | J32: =IF(OR($G32="",SUM($H$7:$H$36)=0),"",H32/SUM($H$7:$H$36))
G33: =IF(Setup!B40="","",Setup!B40) | H33: =IF($G33="","",SUMIFS(Income!$F$7:$F$506,Income!$C$7:$C$506,$G33,Income!$B$7:$B$506,">="&DATE(Setup!$C$6,1,1),Income!$B$7:$B$506,"<"&DATE(Setup!$C$6+1,1,1))) | I33: =IF($G33="","",COUNTIFS(Income!$C$7:$C$506,$G33,Income!$B$7:$B$506,">="&DATE(Setup!$C$6,1,1),Income!$B$7:$B$506,"<"&DATE(Setup!$C$6+1,1,1))) | J33: =IF(OR($G33="",SUM($H$7:$H$36)=0),"",H33/SUM($H$7:$H$36))
G34: =IF(Setup!B41="","",Setup!B41) | H34: =IF($G34="","",SUMIFS(Income!$F$7:$F$506,Income!$C$7:$C$506,$G34,Income!$B$7:$B$506,">="&DATE(Setup!$C$6,1,1),Income!$B$7:$B$506,"<"&DATE(Setup!$C$6+1,1,1))) | I34: =IF($G34="","",COUNTIFS(Income!$C$7:$C$506,$G34,Income!$B$7:$B$506,">="&DATE(Setup!$C$6,1,1),Income!$B$7:$B$506,"<"&DATE(Setup!$C$6+1,1,1))) | J34: =IF(OR($G34="",SUM($H$7:$H$36)=0),"",H34/SUM($H$7:$H$36))
G35: =IF(Setup!B42="","",Setup!B42) | H35: =IF($G35="","",SUMIFS(Income!$F$7:$F$506,Income!$C$7:$C$506,$G35,Income!$B$7:$B$506,">="&DATE(Setup!$C$6,1,1),Income!$B$7:$B$506,"<"&DATE(Setup!$C$6+1,1,1))) | I35: =IF($G35="","",COUNTIFS(Income!$C$7:$C$506,$G35,Income!$B$7:$B$506,">="&DATE(Setup!$C$6,1,1),Income!$B$7:$B$506,"<"&DATE(Setup!$C$6+1,1,1))) | J35: =IF(OR($G35="",SUM($H$7:$H$36)=0),"",H35/SUM($H$7:$H$36))
G36: =IF(Setup!B43="","",Setup!B43) | H36: =IF($G36="","",SUMIFS(Income!$F$7:$F$506,Income!$C$7:$C$506,$G36,Income!$B$7:$B$506,">="&DATE(Setup!$C$6,1,1),Income!$B$7:$B$506,"<"&DATE(Setup!$C$6+1,1,1))) | I36: =IF($G36="","",COUNTIFS(Income!$C$7:$C$506,$G36,Income!$B$7:$B$506,">="&DATE(Setup!$C$6,1,1),Income!$B$7:$B$506,"<"&DATE(Setup!$C$6+1,1,1))) | J36: =IF(OR($G36="",SUM($H$7:$H$36)=0),"",H36/SUM($H$7:$H$36))
